nb2dbpy/__init__.py
nb2dbpy/converters.py
nb2dbpy/nb2dbpy.py
nb2dbpy-0.1.0.dist-info/entry_points.txt
nb2dbpy-0.1.0.dist-info/LICENCE
nb2dbpy-0.1.0.dist-info/METADATA
nb2dbpy-0.1.0.dist-info/WHEEL
nb2dbpy-0.1.0.dist-info/RECORD
